midonetclient/__init__.py
midonetclient/admin_state_up_mixin.py
midonetclient/api.py
midonetclient/api_lib.py
midonetclient/application.py
midonetclient/auth_lib.py
midonetclient/bgp_network.py
midonetclient/bgp_peer.py
midonetclient/bridge.py
midonetclient/chain.py
midonetclient/client.py
midonetclient/condition.py
midonetclient/dhcp_host.py
midonetclient/dhcp_subnet.py
midonetclient/exc.py
midonetclient/health_monitor.py
midonetclient/host.py
midonetclient/host_interface.py
midonetclient/host_interface_port.py
midonetclient/httpclient.py
midonetclient/ip_addr_group.py
midonetclient/ip_addr_group_addr.py
midonetclient/l2insertion.py
midonetclient/l2service.py
midonetclient/load_balancer.py
midonetclient/mac_ip.py
midonetclient/mirror.py
midonetclient/pool.py
midonetclient/pool_member.py
midonetclient/pool_statistic.py
midonetclient/port.py
midonetclient/port_group.py
midonetclient/port_group_port.py
midonetclient/port_type.py
midonetclient/resource_base.py
midonetclient/route.py
midonetclient/router.py
midonetclient/rule.py
midonetclient/service_container.py
midonetclient/service_container_group.py
midonetclient/system_state.py
midonetclient/tenant.py
midonetclient/tracerequest.py
midonetclient/tunnel_zone.py
midonetclient/tunnel_zone_host.py
midonetclient/url_provider.py
midonetclient/util.py
midonetclient/vendor_media_type.py
midonetclient/vip.py
midonetclient/vtep.py
midonetclient/vtep_binding.py
midonetclient/vtep_port.py
midonetclient/neutron/__init__.py
midonetclient/neutron/bgp.py
midonetclient/neutron/bridge.py
midonetclient/neutron/chain_rule.py
midonetclient/neutron/client.py
midonetclient/neutron/dhcp.py
midonetclient/neutron/firewall.py
midonetclient/neutron/gateway_device.py
midonetclient/neutron/host.py
midonetclient/neutron/ipaddr_group.py
midonetclient/neutron/l2gw.py
midonetclient/neutron/l3.py
midonetclient/neutron/loadbalancer.py
midonetclient/neutron/media_type.py
midonetclient-5.1.0.dist-info/DESCRIPTION.rst
midonetclient-5.1.0.dist-info/LICENSE.txt
midonetclient-5.1.0.dist-info/METADATA
midonetclient-5.1.0.dist-info/RECORD
midonetclient-5.1.0.dist-info/WHEEL
midonetclient-5.1.0.dist-info/metadata.json
midonetclient-5.1.0.dist-info/pbr.json
midonetclient-5.1.0.dist-info/top_level.txt
