Metadata-Version: 2.0
Name: midonetclient
Version: 5.1.0
Summary: Midonet API client library for Python applications
Home-page: https://github.com/midonet/python-midonetclient
Author: Midokura Engineers
Author-email: midonet-dev@midonet.org
License: Apache License, Version 2.0
Keywords: MidoNet midonetclient python-midonetclient
Platform: UNKNOWN
Classifier: Development Status :: 4 - Beta
Classifier: Intended Audience :: Developers
Classifier: Intended Audience :: System Administrators
Classifier: Intended Audience :: Telecommunications Industry
Classifier: License :: OSI Approved :: Apache Software License
Classifier: Topic :: System :: Networking
Classifier: Topic :: System :: Shells
Classifier: Topic :: Utilities
Requires-Dist: httplib2
Requires-Dist: webob
